lin/__init__.py
lin/adapter.py
lin/common.py
sllin-0.0.1.dist-info/LICENSE
sllin-0.0.1.dist-info/METADATA
sllin-0.0.1.dist-info/WHEEL
sllin-0.0.1.dist-info/top_level.txt
sllin-0.0.1.dist-info/RECORD
