Metadata-Version: 2.1
Name: sllin
Version: 0.0.1
Summary: An alternative python lib for SLCAN based LIN adapters
Home-page: https://gitlab.com/menschel/sllin
Author: Patrick Menschel
Author-email: menschel.p@posteo.de
License: UNKNOWN
Keywords: LIN
Platform: UNKNOWN
Classifier: Development Status :: 4 - Beta
Classifier: Programming Language :: Python :: 3 :: Only
Classifier: License :: Free for non-commercial use
Classifier: Intended Audience :: Developers
Classifier: Topic :: Scientific/Engineering
Classifier: Topic :: Software Development :: Embedded Systems
Requires: pyserial
Requires-Python: >=3.9
License-File: LICENSE
